rouche/__init__.py
rouche/py.typed
rouche-0.0.0.dist-info/METADATA
rouche-0.0.0.dist-info/WHEEL
rouche-0.0.0.dist-info/licenses/LICENSE.md
rouche-0.0.0.dist-info/RECORD
